sdcfc/PKCS12viewer.py
sdcfc/__init__.py
sdcfc/sdcfc.py
sdcfc/testing_sdfc.py
sdcfc/converters/__init__.py
sdcfc/converters/der_to_pem.py
sdcfc/converters/der_to_pkcs12.py
sdcfc/converters/pem_to_der.py
sdcfc/converters/pem_to_pkcs12.py
sdcfc/converters/pkcs12_to_pem.py
sdcfc-0.1.2.dist-info/METADATA
sdcfc-0.1.2.dist-info/WHEEL
sdcfc-0.1.2.dist-info/entry_points.txt
sdcfc-0.1.2.dist-info/top_level.txt
sdcfc-0.1.2.dist-info/RECORD
