Metadata-Version: 2.1
Name: sdcfc
Version: 0.1.2
Summary: SDCFC(Secure Data Certificate Format Converter) This tool converts certs from one format(PEM, DER, PKCS12) files to other formats(PEM, DER, PKCS12).
Home-page: https://github.com/shubham10divakar/sdcfc
Author: Subham Divakar
Author-email: shubham.divakar@gmail.com
License: UNKNOWN
Platform: UNKNOWN
Classifier: Programming Language :: Python :: 3
Classifier: License :: OSI Approved :: MIT License
Classifier: Operating System :: OS Independent
Requires-Dist: cryptography
Requires-Dist: pyOpenSSL
